score.pyramid-0.1-py3.4-nspkg.pth
score/pyramid/__init__.py
score/pyramid/scaffolds/__init__.py
score/pyramid/scaffolds/__pycache__/__init__.cpython-33.pyc
score/pyramid/scaffolds/__pycache__/__init__.cpython-34.pyc
score/pyramid/scaffolds/score/README.txt
score/pyramid/scaffolds/score/development.ini_tmpl
score/pyramid/scaffolds/score/production.ini_tmpl
score/pyramid/scaffolds/score/setup.cfg_tmpl
score/pyramid/scaffolds/score/setup.py_tmpl
score/pyramid/scaffolds/score/+package+/__init__.py
score/pyramid/scaffolds/score/+package+/db/__init__.py
score/pyramid/scaffolds/score/+package+/db/base.py
score/pyramid/scaffolds/score/+package+/page/__init__.py
score/pyramid/scaffolds/score/+package+/page/dev.html
score/pyramid/scaffolds/score/+package+/page/dev.py
score/pyramid/scaffolds/score/+package+/scripts/__init__.py
score/pyramid/scaffolds/score/+package+/scripts/db.py_tmpl
score/pyramid/scaffolds/score/+package+/scripts/shell.py_tmpl
score/pyramid/scaffolds/score/+package+/tpl/_page.jinja2
score/pyramid/scaffolds/score/+package+/tpl/css/_vars.scss
score/pyramid/scaffolds/score/+package+/tpl/css/page.scss
score/pyramid/scaffolds/score/+package+/tpl/css/reset.css
score/pyramid/scaffolds/score/+package+/tpl/dev/checklist.jinja2
score/pyramid/scaffolds/score/+package+/tpl/dev/includetest.jinja2
score/pyramid/scaffolds/score/+package+/tpl/dev/rendertest.jinja2
score/pyramid/scaffolds/score/+package+/tpl/js/test.js
score.pyramid-0.1.dist-info/DESCRIPTION.rst
score.pyramid-0.1.dist-info/METADATA
score.pyramid-0.1.dist-info/RECORD
score.pyramid-0.1.dist-info/WHEEL
score.pyramid-0.1.dist-info/entry_points.txt
score.pyramid-0.1.dist-info/metadata.json
score.pyramid-0.1.dist-info/namespace_packages.txt
score.pyramid-0.1.dist-info/top_level.txt
